importation/__init__.py
importation-0.0.1.dist-info/LICENSE
importation-0.0.1.dist-info/METADATA
importation-0.0.1.dist-info/WHEEL
importation-0.0.1.dist-info/top_level.txt
importation-0.0.1.dist-info/RECORD
