Metadata-Version: 2.1
Name: importation
Version: 0.0.1
Summary: automagically install imports
Home-page: https://github.com/cs01/importation
Author: Chad Smith
Author-email: grassfedcode@gmail.com
License: License :: OSI Approved :: MIT License
Project-URL: Documentation, https://github.com/cs01/importation
Project-URL: Source Code, https://github.com/cs01/importation
Project-URL: Bug Tracker, https://github.com/cs01/importation/issues
Keywords: import,importation,magic,cli,PEP-582,Virtual Environment
Platform: UNKNOWN
Classifier: Operating System :: OS Independent
Classifier: License :: OSI Approved :: MIT License
Classifier: Programming Language :: Python
Classifier: Programming Language :: Python :: 3 :: Only
